arduino/__init__.py
arduino/core.py
arduino/motor.py
python_arduino-0.0.5.dist-info/LICENSE
python_arduino-0.0.5.dist-info/METADATA
python_arduino-0.0.5.dist-info/WHEEL
python_arduino-0.0.5.dist-info/top_level.txt
python_arduino-0.0.5.dist-info/RECORD
