Metadata-Version: 2.1
Name: python-arduino
Version: 0.0.5
Summary: An API for controlling Arduino boards.
Home-page: https://github.com/phuang1024/python-arduino
Author: Patrick Huang
Author-email: huangpatrick16777216@gmail.com
License: UNKNOWN
Platform: UNKNOWN
Classifier: Programming Language :: Python :: 3
Classifier: License :: OSI Approved :: GNU General Public License v2 or later (GPLv2+)
Classifier: Operating System :: OS Independent
Requires-Dist: pyfirmata
